immaterial/__init__.py
immaterial/field_renderers.py
immaterial-0.0.1.dist-info/DESCRIPTION.rst
immaterial-0.0.1.dist-info/METADATA
immaterial-0.0.1.dist-info/RECORD
immaterial-0.0.1.dist-info/WHEEL
immaterial-0.0.1.dist-info/metadata.json
immaterial-0.0.1.dist-info/top_level.txt
